felis/__init__.py
felis/cli.py
felis/datamodel.py
felis/diff.py
felis/metadata.py
felis/py.typed
felis/tap_schema.py
felis/types.py
felis/config/tap_schema/columns.csv
felis/config/tap_schema/key_columns.csv
felis/config/tap_schema/keys.csv
felis/config/tap_schema/schemas.csv
felis/config/tap_schema/tables.csv
felis/config/tap_schema/tap_schema_extensions.yaml
felis/config/tap_schema/tap_schema_std.yaml
felis/db/__init__.py
felis/db/_dialects.py
felis/db/_sqltypes.py
felis/db/_variants.py
felis/db/database_context.py
felis/tests/__init__.py
felis/tests/postgresql.py
felis/tests/run_cli.py
lsst_felis-30.2026.400.dist-info/licenses/COPYRIGHT
lsst_felis-30.2026.400.dist-info/licenses/LICENSE
lsst_felis-30.2026.400.dist-info/METADATA
lsst_felis-30.2026.400.dist-info/WHEEL
lsst_felis-30.2026.400.dist-info/entry_points.txt
lsst_felis-30.2026.400.dist-info/top_level.txt
lsst_felis-30.2026.400.dist-info/zip-safe
lsst_felis-30.2026.400.dist-info/RECORD
