Metadata-Version: 2.4
Name: lsst-felis
Version: 30.2026.400
Summary: A vocabulary for describing catalogs and acting on those descriptions
Author-email: Rubin Observatory Data Management <dm-admin@lists.lsst.org>
License-Expression: GPL-3.0-or-later
Project-URL: Homepage, https://felis.lsst.io
Project-URL: Source, https://github.com/lsst/felis
Keywords: lsst
Classifier: Intended Audience :: Science/Research
Classifier: Operating System :: OS Independent
Classifier: Programming Language :: Python :: 3
Classifier: Programming Language :: Python :: 3.11
Classifier: Programming Language :: Python :: 3.12
Classifier: Programming Language :: Python :: 3.13
Classifier: Programming Language :: Python :: 3.14
Classifier: Topic :: Scientific/Engineering :: Astronomy
Requires-Python: >=3.11.0
License-File: COPYRIGHT
License-File: LICENSE
Requires-Dist: alembic
Requires-Dist: astropy
Requires-Dist: click
Requires-Dist: deepdiff
Requires-Dist: lsst-resources
Requires-Dist: lsst-utils
Requires-Dist: numpy
Requires-Dist: pydantic<3,>=2
Requires-Dist: pyyaml
Requires-Dist: sqlalchemy
Provides-Extra: test
Requires-Dist: pytest>=3.2; extra == "test"
Provides-Extra: dev
Requires-Dist: documenteer[guide]<2; extra == "dev"
Requires-Dist: autodoc_pydantic; extra == "dev"
Requires-Dist: sphinx-click; extra == "dev"
Dynamic: license-file
